plover_retro_everything/__init__.py
plover_retro_everything-0.0.3.dist-info/METADATA
plover_retro_everything-0.0.3.dist-info/WHEEL
plover_retro_everything-0.0.3.dist-info/entry_points.txt
plover_retro_everything-0.0.3.dist-info/top_level.txt
plover_retro_everything-0.0.3.dist-info/zip-safe
plover_retro_everything-0.0.3.dist-info/RECORD
