Metadata-Version: 2.1
Name: plover-retro-everything
Version: 0.0.3
Summary: Surround words you previously typed with arbitrary translations, allowing you to turn most mode-switching plugin into a retro-plugin!
Home-page: https://github.com/elkowar/plover_retro_everything
Author: ElKowar
License: MIT
Keywords: plover_plugin plover
Platform: UNKNOWN
Requires-Dist: plover (>=4.0.0.dev6)
